Workbook

Sheet Start here
B3: Strategy to Systems. Delivered.
B5: NIST AI RMF starter profile
B6: A self assessment against the four functions of the NIST AI Risk Management Framework, sized for a company that does not have an AI risk team.
B8: What this is
B9: NIST calls a tailored application of the framework a Profile. This workbook is a starter profile. It takes the four functions of AI RMF 1.0 and turns each one into outcomes you can rate, own and evidence.
B10: It is not a compliance test. Nobody certifies anyone against the AI RMF, and no score here proves anything to a regulator. What it produces is a ranked list of the gaps that matter most in your business.
B12: How to use it
B13: 1. Work through the Profile assessment tab. Twenty six outcomes, grouped by function.
B14: 2. Rate each one from 0 to 3 using the Rating scale tab. Rate what is true today, not what is planned.
B15: 3. Name an owner for every outcome you rate 2 or 3. An outcome with no owner is not really operating.
B16: 4. Record where the evidence sits. A rating with no evidence location is an opinion.
B17: 5. Read the Summary tab. It tells you which function is weakest and where the unowned rows are.
... B38: Every source used to build this workbook is published by NIST and listed with links on the Sources tab.

Sheet Profile assessment
A2: Strategy to Systems. Delivered.
A3: NIST AI RMF starter profile
A4: Yellow columns are inputs. Blue columns calculate. Rate what is true today.
A5: consult-ds.com
A7: Ref | B7: Function | C7: Outcome | D7: What good looks like | E7: Rating 0-3 | F7: What that means | G7: Owner | H7: Evidence location | I7: Next step
A8: GOV-01 | B8: Govern | C8: One named person is accountable for AI risk across the business. | D8: A name, not a committee without a chair. They do not have to do the work, but they answer for it. | E8: 1 | F8: =IF($E8="","",IFERROR(INDEX('Rating scale'!$C$6:$C$9,MATCH($E8,'Rating scale'!$B$6:$B$9,0)),"Use 0 to 3")) -> Ad hoc | G8: Head of technology | H8: Not documented anywhere yet | I8: Put the name in the board pack for October
A9: GOV-02 | B9: Govern | C9: There is a written statement of what the business will and will not use AI for. | D9: Short and specific. Two pages that name real situations beat twenty pages of principle. | F9: =IF($E9="","",IFERROR(INDEX('Rating scale'!$C$6:$C$9,MATCH($E9,'Rating scale'!$B$6:$B$9,0)),"Use 0 to 3"))
A10: GOV-03 | B10: Govern | C10: Risk tolerance is written in terms someone can apply on a Tuesday. | D10: For example: where a wrong output costs money or reputation, a named person signs it off before it goes out. | F10: =IF($E10="","",IFERROR(INDEX('Rating scale'!$C$6:$C$9,MATCH($E10,'Rating scale'!$B$6:$B$9,0)),"Use 0 to 3"))
A11: GOV-04 | B11: Govern | C11: Building, owning and reviewing an AI use are three different people. | D11: The person who configured it should not be the only person judging whether it works. | F11: =IF($E11="","",IFERROR(INDEX('Rating scale'!$C$6:$C$9,MATCH($E11,'Rating scale'!$B$6:$B$9,0)),"Use 0 to 3"))
A12: GOV-05 | B12: Govern | C12: Staff know enough about the AI they use to notice a wrong answer. | D12: Not training courses. Whether the people using it can tell when it is confidently wrong. | F12: =IF($E12="","",IFERROR(INDEX('Rating scale'!$C$6:$C$9,MATCH($E12,'Rating scale'!$B$6:$B$9,0)),"Use 0 to 3"))
A13: GOV-06 | B13: Govern | C13: Third party AI is covered by the same rules as anything built in house. | D13: Including AI features that appeared in software you already licensed, which nobody approved. | F13: =IF($E13="","",IFERROR(INDEX('Rating scale'!$C$6:$C$9,MATCH($E13,'Rating scale'!$B$6:$B$9,0)),"Use 0 to 3"))
A14: GOV-07 | B14: Govern | C14: Someone can raise a concern about an AI output without going through the person who deployed it. | D14: A route that does not depend on the goodwill of the owner of the system. | F14: =IF($E14="","",IFERROR(INDEX('Rating scale'!$C$6:$C$9,MATCH($E14,'Rating scale'!$B$6:$B$9,0)),"Use 0 to 3"))
A15: MAP-01 | B15: Map | C15: There is a current list of every place AI is used or planned. | D15: One row per use. Current means someone updated it this quarter, not at the last audit. | F15: =IF($E15="","",IFERROR(INDEX('Rating scale'!$C$6:$C$9,MATCH($E15,'Rating scale'!$B$6:$B$9,0)),"Use 0 to 3"))
A16: MAP-02 | B16: Map | C16: Each use is described by what it is for, not by which vendor supplies it. | D16: The same model summarising notes and ranking candidates are two different uses with different risk. | F16: =IF($E16="","",IFERROR(INDEX('Rating scale'!$C$6:$C$9,MATCH($E16,'Rating scale'!$B$6:$B$9,0)),"Use 0 to 3"))
A17: MAP-03 | B17: Map | C17: Who is affected by each use is written down. | D17: Including people who are not customers: applicants, suppliers, employees, patients, students. | F17: =IF($E17="","",IFERROR(INDEX('Rating scale'!$C$6:$C$9,MATCH($E17,'Rating scale'!$B$6:$B$9,0)),"Use 0 to 3"))
A18: MAP-04 | B18: Map | C18: The consequence of a wrong output is described in business terms for each use. | D18: Wrong invoice, wrong candidate rejected, wrong stock number. Not the word inaccuracy. | F18: =IF($E18="","",IFERROR(INDEX('Rating scale'!$C$6:$C$9,MATCH($E18,'Rating scale'!$B$6:$B$9,0)),"Use 0 to 3"))
A19: MAP-05 | B19: Map | C19: Uses that arrived as features in existing software are captured, not only approved projects. | D19: Check expense reports and card statements, not just the IT asset list. | F19: =IF($E19="","",IFERROR(INDEX('Rating scale'!$C$6:$C$9,MATCH($E19,'Rating scale'!$B$6:$B$9,0)),"Use 0 to 3"))
A20: MAP-06 | B20: Map | C20: The data feeding each use is known, including whether it contains personal data. | D20: This is the row that connects AI governance to your DPDP or GDPR obligations. | F20: =IF($E20="","",IFERROR(INDEX('Rating scale'!$C$6:$C$9,MATCH($E20,'Rating scale'!$B$6:$B$9,0)),"Use 0 to 3"))
... A33: MAN-06 | B33: Manage | C33: A decision to accept a risk is recorded, with who accepted it and when. | D33: Accepted risk is a legitimate answer. Unrecorded accepted risk is an argument waiting to happen. | F33: =IF($E33="","",IFERROR(INDEX('Rating scale'!$C$6:$C$9,MATCH($E33,'Rating scale'!$B$6:$B$9,0)),"Use 0 to 3"))
A35: Rate what is true today. A generous rating produces a comfortable summary and no useful next step.

Sheet Rating scale
B2: Strategy to Systems. Delivered.
B3: Rating scale
B4: Four points. Deliberately no half marks.
B5: Rating | C5: Label | D5: What it means
B6: 0 | C6: Not started | D6: Nobody has done this and nobody is assigned to it.
B7: 1 | C7: Ad hoc | D7: It happens sometimes, because a particular person cares. It would stop if they left.
B8: 2 | C8: Defined | D8: It is written down and someone owns it. It may not be running on a rhythm yet.
B9: 3 | C9: Operating | D9: It runs on a stated rhythm, produces evidence, and someone would notice if it stopped.
B11: How to use the scale honestly
B12: The gap between 1 and 2 is documentation. The gap between 2 and 3 is rhythm and evidence.
B13: Most organisations starting this work score 1 across most rows. That is a normal starting position, not a failure.
B14: A profile with no zeros and no ones on the first pass usually means the rating was done by the person who would be embarrassed by a low score.
B16: There is no passing score
B17: The AI RMF sets no threshold and NIST issues no certification against it. The output that matters is the list of rows sitting at 0 or 1 in the function you depend on most.

Sheet Crosswalk
B2: Strategy to Systems. Delivered.
B3: Crosswalk
B4: Orientation, not a control mapping. Use it to find which document to go and read.
B5: AI RMF function | C5: What it asks of you | D5: EU AI Act | E5: ISO/IEC 42001 | F5: India DPDP Act
B6: Govern | C6: Accountability, policy, risk tolerance, staff capability, and rules that cover third party AI. | D6: AI literacy duties and the provider or deployer distinction. Your role determines your obligations. | E6: The management system itself. This is the part that is certifiable, and the reason firms adopt both. | F6: Accountability of the data fiduciary, and the duty to have someone answerable for personal data.
B7: Map | C7: Knowing what AI you run, what it is for, who it affects and what a wrong output costs. | D7: Classification by purpose into risk tiers, plus the separate transparency triggers. | E7: Scope of the management system and identification of AI systems within it. | F7: Purpose limitation and knowing which processing involves personal data.
B8: Measure | C8: Testing whether a system works, on a rhythm, across the groups it affects. | D8: Testing, logging and post market monitoring duties where high risk obligations apply. | E8: Performance evaluation, internal audit and monitoring. | F8: Accuracy and completeness duties where personal data drives a decision.
B9: Manage | C9: Prioritising, responding to incidents, real human review, fallback, and recorded risk acceptance. | D9: Human oversight, corrective action and incident reporting where high risk obligations apply. | E9: Operational controls, nonconformity handling and continual improvement. | F9: Breach notification and the security safeguards duty.
B12: Read this as orientation
B13: The columns are not equivalent and doing one does not discharge another. The AI RMF is voluntary and describes practice. The EU AI Act is law with dates and penalties. ISO/IEC 42001 is a certifiable management system standard. The DPDP Act governs personal data, which most AI uses touch somewhere.
B14: NIST publishes formal crosswalk documents mapping the AI RMF to other frameworks. They are linked on the Sources tab and are the right place to go if you need a control level mapping.
B16: Two things worth knowing before someone sells you either
B17: There is no NIST AI RMF certification. Anyone offering one is selling ISO/IEC 42001, or selling nothing.
B18: EU AI Act dates have moved more than once. Verify them at the source rather than from a summary, including ours.

Sheet Summary
B2: Strategy to Systems. Delivered.
B3: Summary
B4: Calculates from the assessment. Nothing to fill in here.
B5: Function | C5: Rated | D5: Average | E5: Rows still at 0 or 1
B6: Govern | C6: =COUNTIFS('Profile assessment'!$B$8:$B$33,$B6,'Profile assessment'!$E$8:$E$33,">=0") -> 1 | D6: =IFERROR(ROUND(SUMIFS('Profile assessment'!$E$8:$E$33,'Profile assessment'!$B$8:$B$33,$B6)/COUNTIFS('Profile assessment'!$B$8:$B$33,$B6,'Profile assessment'!$E$8:$E$33,">=0"),1),"") -> 1 | E6: =COUNTIFS('Profile assessment'!$B$8:$B$33,$B6,'Profile assessment'!$E$8:$E$33,"<=1") -> 1
B7: Map | C7: =COUNTIFS('Profile assessment'!$B$8:$B$33,$B7,'Profile assessment'!$E$8:$E$33,">=0") -> 0 | D7: =IFERROR(ROUND(SUMIFS('Profile assessment'!$E$8:$E$33,'Profile assessment'!$B$8:$B$33,$B7)/COUNTIFS('Profile assessment'!$B$8:$B$33,$B7,'Profile assessment'!$E$8:$E$33,">=0"),1),"") | E7: =COUNTIFS('Profile assessment'!$B$8:$B$33,$B7,'Profile assessment'!$E$8:$E$33,"<=1") -> 0
B8: Measure | C8: =COUNTIFS('Profile assessment'!$B$8:$B$33,$B8,'Profile assessment'!$E$8:$E$33,">=0") -> 0 | D8: =IFERROR(ROUND(SUMIFS('Profile assessment'!$E$8:$E$33,'Profile assessment'!$B$8:$B$33,$B8)/COUNTIFS('Profile assessment'!$B$8:$B$33,$B8,'Profile assessment'!$E$8:$E$33,">=0"),1),"") | E8: =COUNTIFS('Profile assessment'!$B$8:$B$33,$B8,'Profile assessment'!$E$8:$E$33,"<=1") -> 0
B9: Manage | C9: =COUNTIFS('Profile assessment'!$B$8:$B$33,$B9,'Profile assessment'!$E$8:$E$33,">=0") -> 0 | D9: =IFERROR(ROUND(SUMIFS('Profile assessment'!$E$8:$E$33,'Profile assessment'!$B$8:$B$33,$B9)/COUNTIFS('Profile assessment'!$B$8:$B$33,$B9,'Profile assessment'!$E$8:$E$33,">=0"),1),"") | E9: =COUNTIFS('Profile assessment'!$B$8:$B$33,$B9,'Profile assessment'!$E$8:$E$33,"<=1") -> 0
B10: Total outcomes rated | C10: =COUNTIF('Profile assessment'!$E$8:$E$33,">=0") -> 1 | E10: Out of 26
B12: Where to start
B13: Weakest function | C13: =IFERROR(INDEX($B$6:$B$9,MATCH(MIN($D$6:$D$9),$D$6:$D$9,0)),"Rate some rows first") -> Govern | E13: Not necessarily the one to fix first. Fix the function your business depends on most.
B15: Gaps worth closing
B16: Rows rated 2 or 3 with no owner | C16: =SUMPRODUCT(('Profile assessment'!$E$8:$E$33>=2)*('Profile assessment'!$G$8:$G$33="")) -> 0 | E16: An outcome nobody owns is not operating, whatever it was rated.
B17: Rows rated 2 or 3 with no evidence location | C17: =SUMPRODUCT(('Profile assessment'!$E$8:$E$33>=2)*('Profile assessment'!$H$8:$H$33="")) -> 0 | E17: A rating with no evidence behind it will not survive the first customer questionnaire.
B18: Rows not yet rated | C18: =IF(26-COUNT('Profile assessment'!$E$8:$E$33)<0,0,26-COUNT('Profile assessment'!$E$8:$E$33)) -> 25 | E18: An unrated row is usually a row nobody could answer, which is itself the finding.
B20: Reading the result
B21: A low average across Map means you do not yet know what you run. Nothing downstream of that is reliable, including a high score on Govern.
B22: A high Govern score with a low Manage score is the commonest pattern. It means the policy exists and nothing happens differently on the ground.
B23: The useful output is not the average. It is the list of rows at 0 or 1 attached to the AI use your business would most regret getting wrong.

Sheet Sources
B2: Strategy to Systems. Delivered.
B3: Sources
B4: All primary, all published by NIST. Verified 8 September 2026.
B5: Document | C5: Link | D5: Why it matters
B6: AI RMF 1.0 (NIST AI 100-1), January 2023 | C6: https://nvlpubs.nist.gov/nistpubs/ai/NIST.AI.100-1.pdf | D6: The framework itself. Around forty pages. The four functions and the trustworthiness characteristics are here.
B7: NIST AI RMF programme page | C7: https://www.nist.gov/itl/ai-risk-management-framework | D7: The page to check for the current status, including the revision now in progress.
B8: AI RMF Playbook | C8: https://airc.nist.gov/airmf-resources/playbook/ | D8: Suggested actions for each subcategory. Far more operational than the framework. Will be updated after the revision.
B9: AI RMF Core, functions and categories | C9: https://airc.nist.gov/airmf-resources/airmf/5-sec-core/ | D9: Where Govern, Map, Measure and Manage are broken into categories and subcategories.
B10: AI RMF Profiles | C10: https://airc.nist.gov/airmf-resources/airmf/6-sec-profile/ | D10: NIST's own description of what a Profile is. This workbook is a starter profile in that sense.
B11: Generative AI Profile (NIST AI 600-1), July 2024 | C11: https://doi.org/10.6028/NIST.AI.600-1 | D11: Applies the four functions to generative AI risks. Read this if staff are using language models.
B12: Crosswalk documents | C12: https://airc.nist.gov/airmf-resources/crosswalks/ | D12: NIST's formal mappings to other frameworks. The right source for a control level crosswalk.
B13: Trustworthy and Responsible AI Resource Center | C13: https://airc.nist.gov/ | D13: The hub for everything above, including the glossary and technical reports.
B14: Concept note, AI RMF Profile on Trustworthy AI in Critical Infrastructure, April 2026 | C14: https://www.nist.gov/programs-projects/concept-note-ai-rmf-profile-trustworthy-ai-critical-infrastructure | D14: Relevant if you operate in energy, water, healthcare, transport or financial infrastructure.
B15: AI RMF Roadmap | C15: https://airc.nist.gov/airmf-resources/roadmap/ | D15: What NIST intends to develop next. Useful for seeing where the framework is heading.
B18: A note on the revision
B19: NIST states that AI RMF 1.0 is being revised following the White House AI Action Plan of 23 July 2025, which tasked NIST with removing references to misinformation, diversity, equity and inclusion, and climate change. No revised version had been published when this workbook was built.
B20: The four functions are the stable part and are what this workbook is built on. Check the programme page above before quoting any wording from the framework.
B22: Built by DS Consulting. consult-ds.com
